{"s":"https://sharing-api.sls.epilot.io","o":[["getSharingConfiguration","get","/v1/sharing/configurations/{partner_org_id}",[["PartnerOrgIdPath"]]],["updateSharingConfiguration","patch","/v1/sharing/configurations/{partner_org_id}",[["PartnerOrgIdPath"]],1],["deleteSharingConfiguration","delete","/v1/sharing/configurations/{partner_org_id}",[["PartnerOrgIdPath"]]],["assignRoleToConfiguration","put","/v1/sharing/configurations/{partner_org_id}/role",[["PartnerOrgIdPath"]],1],["getSharingConfigurations","get","/v1/sharing/configurations",[["partner_org_ids","q",true,"form",false]]],["searchPartnerSharingConfigurations","post","/v1/sharing/configurations:search",null,1],["getConfigurationsByTemplateRole","get","/v1/sharing/configurations/by-role/{template_role_id}",[["template_role_id","p",true]]],["shareEntityWithPartners","post","/v1/sharing/entities:share",null,1],["shareChildEntityWithPartners","post","/v1/sharing/entities:share-child",null,1],["offerEntityToPartners","post","/v1/sharing/entities:offer",null,1],["getOfferStatus","get","/v1/sharing/offers/status",[["partner_org_id","q",true],["sharing_org_id","q",true],["entity_id","q",true]]],["acceptOffer","post","/v1/sharing/offers:accept",null,1]],"v":"3.0.3","cp":{"PartnerOrgIdPath":["partner_org_id","p",true]}}